mapraster/__init__.py
mapraster/main.py
mapraster-2026.1.6.dist-info/METADATA
mapraster-2026.1.6.dist-info/WHEEL
mapraster-2026.1.6.dist-info/licenses/LICENSE
mapraster-2026.1.6.dist-info/RECORD
