Metadata-Version: 2.4
Name: mapraster
Version: 2026.1.6
Summary: mapraster is a Python lib to interpolate xarray raster field on image geometry (e.g. line/sample)
License: MIT
License-File: LICENSE
Author: umr-lops
Author-email: antoine.grouazel@ifremer.fr
Requires-Python: >=3.9,<4.0
Classifier: Development Status :: 3 - Alpha
Classifier: Intended Audience :: Developers
Classifier: License :: OSI Approved :: MIT License
Classifier: Operating System :: OS Independent
Classifier: Programming Language :: Python :: 3
Classifier: Programming Language :: Python :: 3.9
Classifier: Programming Language :: Python :: 3.10
Classifier: Programming Language :: Python :: 3.11
Classifier: Programming Language :: Python :: 3.12
Classifier: Programming Language :: Python :: 3.13
Classifier: Programming Language :: Python :: 3.14
Classifier: Topic :: Software Development :: Libraries :: Python Modules
Requires-Dist: numpy (>=1.21,<3)
Requires-Dist: scipy (>=1.9.0,<2.0.0)
Requires-Dist: xarray (>=2023.1,<2026)
Project-URL: Homepage, https://github.com/umr-lops/mapraster
Project-URL: Repository, https://github.com/umr-lops/mapraster
